CHANGES
LICENSE
MANIFEST.in
PKG-INFO.rst
README.rst
setup.py
ccore/.cproject
ccore/.project
ccore/CMakeLists.txt
ccore/ccore.mk
ccore/ccore.sln
ccore/makefile
ccore/utcore.mk
ccore/bvt/CMakeLists.txt
ccore/bvt/bvt-shared.vcxproj
ccore/bvt/bvt-static.vcxproj
ccore/bvt/shared-test.cpp
ccore/bvt/static-test.cpp
ccore/external/CMakeLists.txt
ccore/external/include/gtest/gtest.h
ccore/external/libs/linux/x64/.linux.x64.libs
ccore/external/libs/linux/x86/.linux.x86.libs
ccore/external/libs/windows/x64/.win.x64.libs
ccore/external/libs/windows/x86/.win.x86.libs
ccore/external/src/gtest/gtest-all.cpp
ccore/include/pyclustering/definitions.hpp
ccore/include/pyclustering/cluster/agglomerative.hpp
ccore/include/pyclustering/cluster/bsas.hpp
ccore/include/pyclustering/cluster/bsas_data.hpp
ccore/include/pyclustering/cluster/center_initializer.hpp
ccore/include/pyclustering/cluster/clique.hpp
ccore/include/pyclustering/cluster/clique_block.hpp
ccore/include/pyclustering/cluster/clique_data.hpp
ccore/include/pyclustering/cluster/cluster_data.hpp
ccore/include/pyclustering/cluster/cure.hpp
ccore/include/pyclustering/cluster/cure_data.hpp
ccore/include/pyclustering/cluster/dbscan.hpp
ccore/include/pyclustering/cluster/dbscan_data.hpp
ccore/include/pyclustering/cluster/elbow.hpp
ccore/include/pyclustering/cluster/elbow_data.hpp
ccore/include/pyclustering/cluster/fcm.hpp
ccore/include/pyclustering/cluster/fcm_data.hpp
ccore/include/pyclustering/cluster/gmeans.hpp
ccore/include/pyclustering/cluster/gmeans_data.hpp
ccore/include/pyclustering/cluster/hsyncnet.hpp
ccore/include/pyclustering/cluster/kmeans.hpp
ccore/include/pyclustering/cluster/kmeans_data.hpp
ccore/include/pyclustering/cluster/kmeans_plus_plus.hpp
ccore/include/pyclustering/cluster/kmedians.hpp
ccore/include/pyclustering/cluster/kmedians_data.hpp
ccore/include/pyclustering/cluster/kmedoids.hpp
ccore/include/pyclustering/cluster/kmedoids_data.hpp
ccore/include/pyclustering/cluster/mbsas.hpp
pyclustering.egg-info/PKG-INFO
pyclustering.egg-info/SOURCES.txt
pyclustering.egg-info/dependency_links.txt
pyclustering.egg-info/requires.txt
pyclustering.egg-info/top_level.txt
