Metadata-Version: 1.2
Name: pyclustering
Version: 0.10.1
Summary: pyclustring is a python data mining library
Home-page: https://github.com/annoviko/pyclustering
Author: Andrei Novikov
Author-email: pyclustering@yandex.ru
License: BSD-3-Clause
Project-URL: Homepage, https://pyclustering.github.io/
Project-URL: Repository, https://github.com/annoviko/pyclustering
Project-URL: Documentation, https://pyclustering.github.io/docs/0.10.1/html/index.html
Project-URL: Bug Tracker, https://github.com/annoviko/pyclustering/issues
Keywords: pyclustering data-mining clustering cluster-analysis machine-learning neural-network oscillatory-network
Platform: UNKNOWN
Classifier: Development Status :: 5 - Production/Stable
Classifier: Intended Audience :: Developers
Classifier: Intended Audience :: Education
Classifier: Intended Audience :: Information Technology
Classifier: Intended Audience :: Science/Research
Classifier: License :: OSI Approved :: BSD License
Classifier: Natural Language :: English
Classifier: Operating System :: Microsoft
Classifier: Operating System :: Microsoft :: Windows
Classifier: Operating System :: POSIX :: Linux
Classifier: Operating System :: Unix
Classifier: Operating System :: iOS
Classifier: Programming Language :: C
Classifier: Programming Language :: C++
Classifier: Programming Language :: Python :: 3
Classifier: Topic :: Education
Classifier: Topic :: Scientific/Engineering :: Artificial Intelligence
Classifier: Topic :: Scientific/Engineering :: Bio-Informatics
Classifier: Topic :: Scientific/Engineering :: Information Analysis
Classifier: Topic :: Scientific/Engineering :: Visualization
Classifier: Topic :: Software Development :: Libraries
Requires-Python: >=3.6
